.gitignore
LICENSE.rst
MANIFEST.in
README.rst
setup.cfg
setup.py
test_trustpaylib.py
tox.ini
trustpaylib.py
trustpaylib.egg-info/PKG-INFO
trustpaylib.egg-info/SOURCES.txt
trustpaylib.egg-info/dependency_links.txt
trustpaylib.egg-info/top_level.txt