Metadata-Version: 1.1
Name: trustpaylib
Version: 0.0.1
Summary: TrustPay payments integration library.
Home-page: https://github.com/beezz/trustpaylib
Author: Michal Kuffa
Author-email: michal.kuffa@gmail.com
License: BSD
Platform: UNKNOWN
Classifier: Intended Audience :: Developers
Classifier: License :: OSI Approved :: BSD License
Classifier: Operating System :: OS Independent
Classifier: Topic :: Software Development
Classifier: Programming Language :: Python :: 2.6
Classifier: Programming Language :: Python :: 2.7
Classifier: Programming Language :: Python :: 3.2
